csdt_stl_converter/adinkra_converter.py
csdt_stl_converter/image2stl.py
csdt_stl_converter-1.2.1.dist-info/LICENSE
csdt_stl_converter-1.2.1.dist-info/METADATA
csdt_stl_converter-1.2.1.dist-info/WHEEL
csdt_stl_converter-1.2.1.dist-info/entry_points.txt
csdt_stl_converter-1.2.1.dist-info/top_level.txt
csdt_stl_converter-1.2.1.dist-info/RECORD
