Metadata-Version: 2.1
Name: csdt-stl-converter
Version: 1.2.1
Summary: Converts images to stl files
Home-page: https://github.com/CSDTs/Adinkra_extrusion_converter
Author: Andrew Hunn
Author-email: ahunn@umich.edu
License: MIT
Platform: UNKNOWN
Requires-Dist: csdt-stl-tools
Requires-Dist: opencv-python
Requires-Dist: numpy
